odoo/addons/product_brand_purchase/README.rst
odoo/addons/product_brand_purchase/__init__.py
odoo/addons/product_brand_purchase/__manifest__.py
odoo/addons/product_brand_purchase/i18n/it.po
odoo/addons/product_brand_purchase/i18n/product_brand_purchase.pot
odoo/addons/product_brand_purchase/readme/CONTRIBUTORS.rst
odoo/addons/product_brand_purchase/readme/DESCRIPTION.rst
odoo/addons/product_brand_purchase/readme/USAGE.rst
odoo/addons/product_brand_purchase/reports/__init__.py
odoo/addons/product_brand_purchase/reports/purchase_report.py
odoo/addons/product_brand_purchase/reports/purchase_report_view.xml
odoo/addons/product_brand_purchase/static/description/icon.png
odoo/addons/product_brand_purchase/static/description/index.html
odoo/addons/product_brand_purchase/views/product_brand_view.xml
odoo14_addon_product_brand_purchase-14.0.1.0.1.dev5.dist-info/METADATA
odoo14_addon_product_brand_purchase-14.0.1.0.1.dev5.dist-info/WHEEL
odoo14_addon_product_brand_purchase-14.0.1.0.1.dev5.dist-info/top_level.txt
odoo14_addon_product_brand_purchase-14.0.1.0.1.dev5.dist-info/RECORD
